nik/__init__.py
nik/__main__.py
nik/config.py
nik/exceptions.py
nik/helpers.py
nik/logging.py
nik/nik.py
nik/zettel.py
nik/zettelkasten.py
nik/cli/__init__.py
nik/cli/config.py
nik/cli/init.py
nik/cli/open.py
nik/cli/rename.py
nik/cli/show.py
nik/cli/status.py
nik-0.1.0.dist-info/LICENSE
nik-0.1.0.dist-info/METADATA
nik-0.1.0.dist-info/WHEEL
nik-0.1.0.dist-info/entry_points.txt
nik-0.1.0.dist-info/top_level.txt
nik-0.1.0.dist-info/RECORD
