Metadata-Version: 2.1
Name: nik
Version: 0.1.0
Summary: A simplistic, versatile companion to browse, navigate and visualize your text-based Zettelkasten.
Home-page: https://github.com/markus-beuckelmann/nik
Author: Markus Beuckelmann
Author-email: email@markus-beuckelmann.de
License: AGPLv3
Download-URL: https://github.com/markus-beuckelmann/nik/releases/download/0.1.0/nik-0.1.0.tar.gz
Keywords: Zettelkasten nik markdown
Platform: UNKNOWN
Classifier: Programming Language :: Python :: 3
Classifier: Development Status :: 3 - Alpha
Classifier: Intended Audience :: Developers
Classifier: License :: OSI Approved :: GNU Affero General Public License v3
Classifier: License :: OSI Approved
Classifier: Topic :: Text Processing
Classifier: Topic :: Text Processing :: Markup
Classifier: Topic :: Software Development :: Libraries :: Python Modules
Classifier: Topic :: Internet :: WWW/HTTP :: Indexing/Search
Classifier: Topic :: Education
Requires-Python: >=3.7
Requires-Dist: pytest
Requires-Dist: pytest-cov
Requires-Dist: ipython
